bcolors/__init__.py
python_shell_colors-0.4.0.dist-info/COPYING
python_shell_colors-0.4.0.dist-info/METADATA
python_shell_colors-0.4.0.dist-info/WHEEL
python_shell_colors-0.4.0.dist-info/top_level.txt
python_shell_colors-0.4.0.dist-info/RECORD
